MANIFEST.in
README.txt
setup.cfg
setup.py
c2/__init__.py
c2.search.customdescription.egg-info/PKG-INFO
c2.search.customdescription.egg-info/SOURCES.txt
c2.search.customdescription.egg-info/dependency_links.txt
c2.search.customdescription.egg-info/entry_points.txt
c2.search.customdescription.egg-info/namespace_packages.txt
c2.search.customdescription.egg-info/not-zip-safe
c2.search.customdescription.egg-info/requires.txt
c2.search.customdescription.egg-info/top_level.txt
c2/search/__init__.py
c2/search/customdescription/__init__.py
c2/search/customdescription/configure.zcml
c2/search/customdescription/version.txt
c2/search/customdescription/browser/__init__.py
c2/search/customdescription/browser/configure.zcml
c2/search/customdescription/browser/customview.py
c2/search/customdescription/browser/interfaces.py
c2/search/customdescription/profiles/default/catalog.xml
c2/search/customdescription/profiles/default/metadata.xml
c2/search/customdescription/profiles/default/skins.xml
c2/search/customdescription/skins/c2customdescription/highlightsearchterms.js
c2/search/customdescription/skins/c2customdescription/search.pt
c2/search/customdescription/tests/__init__.py
c2/search/customdescription/tests/base.py
c2/search/customdescription/tests/test_setup.py
docs/HISTORY.txt
docs/INSTALL.txt
docs/LICENSE.GPL
docs/LICENSE.txt