Metadata-Version: 1.0
Name: c2.search.customdescription
Version: 1.0b3
Summary: This package gives Google or Yahoo like search result view for Plone.
Home-page: http://www.cmscom.jp
Author: CMScom
Author-email: terada@cmscom.jp
License: GPL
Keywords: plone search description
Platform: UNKNOWN
Classifier: Framework :: Plone
Classifier: Programming Language :: Python
Classifier: Topic :: Software Development :: Libraries :: Python Modules
